e2j2/__init__.py
e2j2/cache.py
e2j2/cli.py
e2j2/constants.py
e2j2/display.py
e2j2/exceptions.py
e2j2/templates.py
e2j2/scripts/__init__.py
e2j2/scripts/e2j2.py
e2j2/tags/__init__.py
e2j2/tags/base64_tag.py
e2j2/tags/consul_tag.py
e2j2/tags/dns_tag.py
e2j2/tags/escape_tag.py
e2j2/tags/file_tag.py
e2j2/tags/json_tag.py
e2j2/tags/jsonfile_tag.py
e2j2/tags/list_tag.py
e2j2/tags/vault_tag.py
tests/__init__.py
tests/conftest.py
tests/test_tags.py
e2j2-0.8.1.dist-info/AUTHORS.rst
e2j2-0.8.1.dist-info/LICENSE
e2j2-0.8.1.dist-info/METADATA
e2j2-0.8.1.dist-info/WHEEL
e2j2-0.8.1.dist-info/entry_points.txt
e2j2-0.8.1.dist-info/top_level.txt
e2j2-0.8.1.dist-info/zip-safe
e2j2-0.8.1.dist-info/RECORD
