Metadata-Version: 2.1
Name: e2j2
Version: 0.8.1
Summary: e2j2 is a commandline utility to render text/configuration files from jinja2 templatesfrom shell environment variables
Home-page: https://gitlab.com/solvinity/e2j2
Author: Johan Bakker
Author-email: johan.bakker@solvinity.com
License: MIT
Classifier: Development Status :: 4 - Beta
Classifier: Intended Audience :: Developers
Classifier: Operating System :: OS Independent
Classifier: License :: OSI Approved :: MIT License
Classifier: Programming Language :: Python :: 3.7
Classifier: Programming Language :: Python :: 3.8
Classifier: Programming Language :: Python :: 3.9
Classifier: Programming Language :: Python :: 3.10
Classifier: Programming Language :: Python :: 3.11
Classifier: Topic :: System :: Systems Administration
Classifier: Topic :: Software Development :: Libraries
License-File: LICENSE
License-File: AUTHORS.rst
Requires-Dist: jinja2 (>=2.10.1)
Requires-Dist: python-consul (>=0.6.0)
Requires-Dist: deepmerge (>=0.0.4)
Requires-Dist: dnspython
Requires-Dist: jsonschema
Requires-Dist: rfc3987
Requires-Dist: munch
Requires-Dist: dpath (>=2.0.1)
Requires-Dist: termcolor (>=1.1.0)
